Swapout.py
Swapout-0.0.1.dist-info/LICENSE
Swapout-0.0.1.dist-info/METADATA
Swapout-0.0.1.dist-info/WHEEL
Swapout-0.0.1.dist-info/top_level.txt
Swapout-0.0.1.dist-info/RECORD
