Metadata-Version: 2.1
Name: Swapout
Version: 0.0.1
Summary: Swapout: Exchanging Pixels for Long-range Spatial Learning
Home-page: https://github.com/shanfenghu/Swapout
Author: Shanfeng Hu
Author-email: shanfeng.hu1991@gmail.com
License: UNKNOWN
Platform: UNKNOWN
Classifier: Programming Language :: Python :: 3
Classifier: License :: OSI Approved :: MIT License
Classifier: Operating System :: OS Independent
Requires-Python: >=3.7
